depths/__init__.py
depths/cli/__init__.py
depths/cli/app.py
depths/cli/cli.py
depths/core/__init__.py
depths/core/aggregator.py
depths/core/config.py
depths/core/logger.py
depths/core/otlp_mapper.py
depths/core/producer.py
depths/core/schema.py
depths/core/shipper.py
depths/core/views.py
depths/io/__init__.py
depths/io/delta.py
depths-0.2.0.dist-info/METADATA
depths-0.2.0.dist-info/WHEEL
depths-0.2.0.dist-info/entry_points.txt
depths-0.2.0.dist-info/licenses/LICENSE
depths-0.2.0.dist-info/RECORD
