Metadata-Version: 2.4
Name: depths
Version: 0.2.0
Summary: S3-native OpenTelemetry compatible observability layer
Project-URL: Homepage, https://github.com/depths-ai/depths
Project-URL: Documentation, https://docs.depthsai.com
Project-URL: Issues, https://github.com/depths-ai/depths/issues
Author-email: Depths AI <admin@depthsai.com>
License-File: LICENSE
Requires-Python: >=3.12
Requires-Dist: boto3>=1.40.36
Requires-Dist: deltalake==1.1.4
Requires-Dist: fastapi>=0.118.0
Requires-Dist: httpx>=0.28.1
Requires-Dist: polars==1.33.1
Requires-Dist: psutil>=7.1.0
Requires-Dist: pyarrow==21.0.0
Requires-Dist: python-dotenv>=1.1.1
Requires-Dist: typer>=0.19.2
Requires-Dist: uvicorn>=0.37.0
Provides-Extra: proto
Requires-Dist: opentelemetry-proto>=1.37.0; extra == 'proto'
Requires-Dist: protobuf>=6.32.1; extra == 'proto'
